jbutils/__init__.py
jbutils/cli_util.py
jbutils/config.py
jbutils/console.py
jbutils/consts.py
jbutils/jb_logging.py
jbutils/models/__init__.py
jbutils/models/attr_dict.py
jbutils/models/base.py
jbutils/models/console_theme.py
jbutils/tools/__init__.py
jbutils/tools/cli.py
jbutils/types.py
jbutils/utils.py
jbutils-0.2.16.dist-info/METADATA
jbutils-0.2.16.dist-info/WHEEL
jbutils-0.2.16.dist-info/entry_points.txt
jbutils-0.2.16.dist-info/RECORD
