Metadata-Version: 2.1
Name: jbutils
Version: 0.2.16
Summary: 
Author: Joseph Bochinski
Author-email: stirgejr@gmail.com
Requires-Python: >=3.10
Classifier: Programming Language :: Python :: 3
Classifier: Programming Language :: Python :: 3.10
Classifier: Programming Language :: Python :: 3.11
Classifier: Programming Language :: Python :: 3.12
Requires-Dist: json5 (>=0.12.1,<0.13.0)
Requires-Dist: jsonlines (>=4.0.0,<5.0.0)
Requires-Dist: pillow (>=11.3.0,<12.0.0)
Requires-Dist: platformdirs (>=4.3.8,<5.0.0)
Requires-Dist: prompt-toolkit (>=3.0.51,<4.0.0)
Requires-Dist: ptpython (>=3.0.30,<4.0.0)
Requires-Dist: pymupdf (>=1.26.4,<2.0.0)
Requires-Dist: rich (>=14.1.0,<15.0.0)
Requires-Dist: ruamel-yaml (>=0.18.10,<0.19.0)
Requires-Dist: tomli (>=2.2.1,<3.0.0)
Requires-Dist: typing-extensions (>=4.14.1,<5.0.0)
